sawdust/__init__.py
sawdust/logging.py
sawdust/py.typed
sawdust-0.1.0.dist-info/LICENSE
sawdust-0.1.0.dist-info/METADATA
sawdust-0.1.0.dist-info/WHEEL
sawdust-0.1.0.dist-info/top_level.txt
sawdust-0.1.0.dist-info/RECORD
