Metadata-Version: 2.1
Name: sawdust
Version: 0.1.0
Summary: A simple logging implementation in Python
Home-page: https://github.com/nwithan8/sawdust
Download-URL: https://github.com/nwithan8/sawdust/archive/refs/tags/0.1.0.tar.gz
Author: Nate Harris
Author-email: n8gr8gbln@gmail.com
License: GNU General Public License v3 (GPLv3)
Keywords: logging,log,logger,logs,log to file,log to console
Classifier: License :: OSI Approved :: GNU General Public License v3 (GPLv3)
Classifier: Development Status :: 4 - Beta
Classifier: Intended Audience :: Developers
Classifier: Topic :: Software Development :: Build Tools
Classifier: Topic :: Multimedia :: Video
Classifier: Topic :: Multimedia
Classifier: Topic :: Internet :: WWW/HTTP
Classifier: Operating System :: OS Independent
Classifier: Programming Language :: Python :: 3
Classifier: Programming Language :: Python :: 3.7
Classifier: Programming Language :: Python :: 3.8
Classifier: Programming Language :: Python :: 3.9
Classifier: Programming Language :: Python :: 3.10
Classifier: Programming Language :: Python :: 3.11
Classifier: Programming Language :: Python :: 3.12
Requires-Python: >=3.7, <4
License-File: LICENSE
Provides-Extra: dev
Requires-Dist: black ; extra == 'dev'
Requires-Dist: flake8 ; extra == 'dev'
Requires-Dist: isort ; extra == 'dev'
Requires-Dist: pytest-cov ==3.* ; extra == 'dev'
Requires-Dist: pytest-vcr ==1.* ; extra == 'dev'
Requires-Dist: pytest ==7.* ; extra == 'dev'
Requires-Dist: types-requests ; extra == 'dev'
Requires-Dist: types-urllib3 ; extra == 'dev'
Requires-Dist: vcrpy ==4.* ; extra == 'dev'
